mhp/MakePolymer.py
mhp/__init__.py
mhp/custom_input_to_mol_file.py
mhp/nb.py
mhp/random_polymer_to_mol_file.py
mhp/settings.py
mhp/smiles.py
mhp-0.1.3.4.dist-info/METADATA
mhp-0.1.3.4.dist-info/WHEEL
mhp-0.1.3.4.dist-info/entry_points.txt
mhp-0.1.3.4.dist-info/top_level.txt
mhp-0.1.3.4.dist-info/RECORD
