Metadata-Version: 2.1
Name: mhp
Version: 0.1.3.4
Summary: Facilitates solubility calculations on a wide range of polymers.
Home-page: https://github.com/scohenjanes5/MHP
Author: Sander Cohen-Janes
Author-email: scohenjanes@brandeis.edu
Classifier: Programming Language :: Python
Classifier: Programming Language :: Python :: 3
Classifier: Programming Language :: Python :: 3.6
Requires-Dist: rdkit
Requires-Dist: scipy
Requires-Dist: pandas
Requires-Dist: matplotlib
